model_helpers.py
model_helpers/__init__.py
model_helpers/cache_helpers.py
model_helpers/key_value_field.py
model_helpers/model_choices.py
model_helpers/upload_to_helpers.py
django_model_helpers-4.0.dist-info/LICENSE
django_model_helpers-4.0.dist-info/METADATA
django_model_helpers-4.0.dist-info/WHEEL
django_model_helpers-4.0.dist-info/top_level.txt
django_model_helpers-4.0.dist-info/RECORD
