Metadata-Version: 2.1
Name: django-model-helpers
Version: 4.0
Summary: Helpful functions and classes for your django app's models
Home-page: https://github.com/ramast/django_model_helpers
Author: Ramast Magdy
Author-email: ramast.com@gmail.com
License: MIT
Keywords: django models keyvaluefield cached_model_property cached_function
Classifier: Development Status :: 4 - Beta
Classifier: Intended Audience :: Developers
Classifier: Topic :: Software Development :: Libraries :: Python Modules
Classifier: License :: OSI Approved :: MIT License
Classifier: Programming Language :: Python :: 3
Classifier: Programming Language :: Python :: 3.4
Classifier: Programming Language :: Python :: 3.5
Classifier: Programming Language :: Python :: 3.6
Classifier: Programming Language :: Python :: 3.7
License-File: LICENSE
Requires-Dist: Django >=1.5.0
